Metadata-Version: 2.4
Name: simple-lama-inpainting-updated
Version: 0.1.3
Author-email: d1c0n <pypi@dickon.it>
License-File: LICENSE
Requires-Python: >=3.12
Requires-Dist: fire>=0.5.0
Requires-Dist: numpy>=1.26.4
Requires-Dist: opencv-python>=4.11.0.86
Requires-Dist: pillow>=9.5.0
Requires-Dist: torch>=2.9.1
Requires-Dist: torchvision>=0.24.1
